qgate_perf/__init__.py
qgate_perf/file_marker.py
qgate_perf/helper.py
qgate_perf/output_result.py
qgate_perf/output_setup.py
qgate_perf/parallel_executor.py
qgate_perf/parallel_probe.py
qgate_perf/percentile_heap.py
qgate_perf/run_return.py
qgate_perf/run_setup.py
qgate_perf/standard_deviation.py
qgate_perf/version.py
qgate_perf-0.4.50.dist-info/LICENSE
qgate_perf-0.4.50.dist-info/METADATA
qgate_perf-0.4.50.dist-info/WHEEL
qgate_perf-0.4.50.dist-info/top_level.txt
qgate_perf-0.4.50.dist-info/RECORD
