Metadata-Version: 2.1
Name: qgate_perf
Version: 0.4.50
Summary: Performance test generator, part of Quality Gate
Author-email: Jiri Steuer <steuer.jiri@gmail.com>
Maintainer-email: Jiri Steuer <steuer.jiri@gmail.com>
License: MIT
Project-URL: homepage, https://github.com/george0st/qgate-perf/
Project-URL: repository, https://pypi.org/project/qgate_perf/
Keywords: PerformanceTest,Performance,QualityGate
Classifier: Development Status :: 5 - Production/Stable
Classifier: Intended Audience :: Developers
Classifier: License :: OSI Approved :: Apache Software License
Classifier: Operating System :: POSIX :: Linux
Classifier: Operating System :: Microsoft :: Windows
Classifier: Operating System :: MacOS
Classifier: Programming Language :: Python :: 3
Classifier: Programming Language :: Python :: 3.6
Classifier: Programming Language :: Python :: 3.7
Classifier: Programming Language :: Python :: 3.8
Classifier: Programming Language :: Python :: 3.9
Classifier: Programming Language :: Python :: 3.10
Classifier: Programming Language :: Python :: 3.11
Classifier: Programming Language :: Python :: 3 :: Only
Classifier: Programming Language :: Python
Classifier: Topic :: Software Development :: Libraries :: Python Modules
Classifier: Topic :: Software Development :: Libraries
Requires-Python: >=3.6
License-File: LICENSE
Requires-Dist: numpy<=2.1.3,>=1.26.4
Requires-Dist: psutil<=6.0.0,>=5.9.0
Requires-Dist: packaging<=24.1,>=21.0
Requires-Dist: qgate-graph==1.4.29
Provides-Extra: dev
Requires-Dist: click~=8.1; extra == "dev"
Requires-Dist: numpy<=2.1.3,>=1.26.4; extra == "dev"
Requires-Dist: psutil<=6.0.0,>=5.9.0; extra == "dev"
Requires-Dist: packaging<=24.1,>=21.0; extra == "dev"
Requires-Dist: qgate-graph==1.4.29; extra == "dev"
Requires-Dist: coverage>=7; extra == "dev"
Requires-Dist: coverage-badge>=1; extra == "dev"
Requires-Dist: pympler==1.0.1; extra == "dev"
